mr_wolf/weather_forecast_chart/__init__.py
mr_wolf/weather_forecast_chart/main.py
mr_wolf.weather_forecast_chart-1.0.0.dist-info/METADATA
mr_wolf.weather_forecast_chart-1.0.0.dist-info/WHEEL
mr_wolf.weather_forecast_chart-1.0.0.dist-info/entry_points.txt
mr_wolf.weather_forecast_chart-1.0.0.dist-info/top_level.txt
mr_wolf.weather_forecast_chart-1.0.0.dist-info/RECORD
