Metadata-Version: 2.1
Name: mr-wolf.weather-forecast-chart
Version: 1.0.0
Summary: Command line tool for downloading the weather forecast charts from http://wetter.com
Home-page: https://bitbucket.org/stefanbunde/mr-wolf/
Author: Stefan Bunde
Author-email: stefanbunde+git@posteo.de
License: AGPLv3+
Platform: UNKNOWN
Classifier: Development Status :: 5 - Production/Stable
Classifier: License :: OSI Approved :: GNU Affero General Public License v3 or later (AGPLv3+)
Classifier: Operating System :: OS Independent
Classifier: Programming Language :: Python
Classifier: Programming Language :: Python :: 3 :: Only
Classifier: Programming Language :: Python :: 3.6
Classifier: Programming Language :: Python :: 3.7
Classifier: Programming Language :: Python :: 3.8
Classifier: Programming Language :: Python :: 3.9
Requires-Python: ~=3.6
Requires-Dist: selenium
